faz/bot/__init__.py
faz/bot/core/__init__.py
faz/bot/core/logger_setup.py
faz/bot/core/properties.py
faz/bot/database/__init__.py
faz/bot/database/fazcord/__init__.py
faz/bot/database/fazcord/fazcord_database.py
faz/bot/database/fazcord/model/__init__.py
faz/bot/database/fazcord/model/base_fazcord_model.py
faz/bot/database/fazcord/model/discord_channel.py
faz/bot/database/fazcord/model/discord_guild.py
faz/bot/database/fazcord/model/discord_user.py
faz/bot/database/fazcord/model/track_entry.py
faz/bot/database/fazcord/model/track_entry_association.py
faz/bot/database/fazcord/model/whitelist_group.py
faz/bot/database/fazcord/repository/__init__.py
faz/bot/database/fazcord/repository/discord_channel_repository.py
faz/bot/database/fazcord/repository/discord_guild_repository.py
faz/bot/database/fazcord/repository/discord_user_repository.py
faz/bot/database/fazcord/repository/track_entry_association_repository.py
faz/bot/database/fazcord/repository/track_entry_repository.py
faz/bot/database/fazcord/repository/whitelist_group_repository.py
faz/bot/database/fazwynn/__init__.py
faz/bot/database/fazwynn/fazwynn_database.py
faz/bot/database/fazwynn/model/__init__.py
faz/bot/database/fazwynn/model/_unique_id_model.py
faz/bot/database/fazwynn/model/base_fazwynn_model.py
faz/bot/database/fazwynn/model/character_history.py
faz/bot/database/fazwynn/model/character_info.py
faz/bot/database/fazwynn/model/fazdb_uptime.py
faz/bot/database/fazwynn/model/guild_history.py
faz/bot/database/fazwynn/model/guild_info.py
faz/bot/database/fazwynn/model/guild_member_history.py
faz/bot/database/fazwynn/model/online_players.py
faz/bot/database/fazwynn/model/player_activity_history.py
faz/bot/database/fazwynn/model/player_history.py
faz/bot/database/fazwynn/model/player_info.py
faz/bot/database/fazwynn/model/worlds.py
faz/bot/database/fazwynn/repository/__init__.py
faz/bot/database/fazwynn/repository/character_history_repository.py
faz/bot/database/fazwynn/repository/character_info_repository.py
faz_bot_core-0.4.1.dist-info/LICENSE
faz_bot_core-0.4.1.dist-info/METADATA
faz_bot_core-0.4.1.dist-info/WHEEL
faz_bot_core-0.4.1.dist-info/entry_points.txt
faz_bot_core-0.4.1.dist-info/top_level.txt
faz_bot_core-0.4.1.dist-info/RECORD
