Metadata-Version: 2.1
Name: faz-bot-core
Version: 0.4.1
Summary: Core logic used by the other faz-bot components.
Author-email: FAZuH <fazuhhh@proton.me>
License: MIT License
Project-URL: Source, https://github.com/FAZuH/faz-bot-core
Project-URL: Issues, https://github.com/FAZuH/faz-bot-core/issues
Project-URL: Documentation, https://github.com/FAZuH/faz-bot-core#readme
Requires-Python: >=3.12
License-File: LICENSE
Requires-Dist: aiohttp>=3.11.7
Requires-Dist: aiomysql>=0.2.0
Requires-Dist: faz-utils>=0.1.2
Requires-Dist: greenlet>=3.1.1
Requires-Dist: loguru>=0.7.2
Requires-Dist: nextcord>=2.6.0
Requires-Dist: numpy>=2.1.3
Requires-Dist: pandas>=2.2.3
Requires-Dist: python-dotenv>=1.0.1
Requires-Dist: sortedcontainers>=2.4.0
Requires-Dist: sqlalchemy>=2.0.36
